LICENSE
README.md
setup.py
q_sdk/__init__.py
q_sdk/exceptions.py
q_sdk/main.py
q_sdk.egg-info/PKG-INFO
q_sdk.egg-info/SOURCES.txt
q_sdk.egg-info/dependency_links.txt
q_sdk.egg-info/requires.txt
q_sdk.egg-info/top_level.txt
q_sdk/objects/__init__.py
q_sdk/objects/base.py
q_sdk/objects/check.py
q_sdk/objects/metric.py
q_sdk/objects/metric_template.py
q_sdk/objects/time_period.py
q_test/__init__.py